machine/__init__.py
machine/helper.py
machine/machine.py
python_docker_machine-0.2.1.dist-info/DESCRIPTION.rst
python_docker_machine-0.2.1.dist-info/METADATA
python_docker_machine-0.2.1.dist-info/RECORD
python_docker_machine-0.2.1.dist-info/WHEEL
python_docker_machine-0.2.1.dist-info/metadata.json
python_docker_machine-0.2.1.dist-info/pbr.json
python_docker_machine-0.2.1.dist-info/top_level.txt
