Metadata-Version: 2.0
Name: python-docker-machine
Version: 0.2.1
Summary: Python wrapper around docker-machine
Home-page: https://github.com/gijzelaerr/python-docker-machine
Author: Gijs Molenaar
Author-email: gijs@pythonic.nl
License: GPL2
Keywords: docker machine docker-machine container
Platform: UNKNOWN
Classifier: Development Status :: 4 - Beta
Classifier: Environment :: Other Environment
Classifier: Intended Audience :: Developers
Classifier: Operating System :: OS Independent
Classifier: Programming Language :: Python
Classifier: Programming Language :: Python :: 2.7
Classifier: Programming Language :: Python :: 3.4
Classifier: Programming Language :: Python :: 3.5
Classifier: Topic :: Utilities
Requires-Dist: docker-py
